sysloss/__init__.py
sysloss/components.py
sysloss/diagram.py
sysloss/system.py
sysloss/utils.py
sysloss-1.10.0.dist-info/LICENSE
sysloss-1.10.0.dist-info/METADATA
sysloss-1.10.0.dist-info/WHEEL
sysloss-1.10.0.dist-info/RECORD
