Metadata-Version: 2.3
Name: sysloss
Version: 1.10.0
Summary: Power tree analysis of circuits, boards and systems.
License: MIT
Keywords: system,power,tree,loss,efficiency,energy,board,component,battery
Author: Geir Drange
Requires-Python: >=3.10,<4.0
Classifier: Development Status :: 5 - Production/Stable
Classifier: Intended Audience :: Developers
Classifier: Intended Audience :: Education
Classifier: Intended Audience :: Science/Research
Classifier: License :: OSI Approved :: MIT License
Classifier: Programming Language :: Python :: 3
Classifier: Programming Language :: Python :: 3.10
Classifier: Programming Language :: Python :: 3.11
Classifier: Programming Language :: Python :: 3.12
Classifier: Programming Language :: Python :: 3.13
Classifier: Topic :: Scientific/Engineering
Classifier: Topic :: Scientific/Engineering :: Electronic Design Automation (EDA)
Requires-Dist: matplotlib (>=3.0,<4.0)
Requires-Dist: packaging (>=21.1)
Requires-Dist: pandas (>=2.0,<3.0)
Requires-Dist: pillow (>=9.3.0)
Requires-Dist: pydot (>=3.0.0)
Requires-Dist: rich (>=12.0)
Requires-Dist: rustworkx (>=0.13)
Requires-Dist: scipy (>=1.9,<2.0)
Requires-Dist: toml (>=0.10.2)
Requires-Dist: tqdm (>=4.63)
Project-URL: Documentation, https://sysloss.readthedocs.io/en/latest/Getting%20started.html#
Project-URL: Homepage, https://github.com/geddy11/sysloss
Project-URL: Repository, https://github.com/geddy11/sysloss
